carry_select_adder/mux.v
module mux4(
    input [3:0] in0, in1,
    input carry0, carry1,
    input sel,
    output [3:0] result,
    output carryout
  );

  /*  MUX structure
  
                        ---------
    in0[4bit]    ------\         \
    in1[4bit]    ------\         \------ result [4bit]
                       \   MUX   \
    carry0[1bit] ------\         \------ carryout [1bit]
    carry1[1bit] ------\         \
                        ----------


  */

  assign result = sel? in1: in0;
  assign carryout = sel? carry1: carry0;

endmodule

module mux16(
  input [15:0] in0,
  input [15:0] in1,
  input mod,
  output [15:0] out
);

assign out = mod? in1: in0;


endmodule

carry_select_adder/fullAdder.v
module adder(
    input a,
    input b,
    input cin,
    output y,
    output cout
  );

  assign y = a + b + cin;
  assign cout = (a & b) + (~a & b & cin) + (a & ~b & cin);

endmodule

carry_select_adder/4bitAdder.v
module fourBitAdder(
    input [3:0] a,
    input [3:0] b,
    input cin,
    output [3:0] y,
    output cout
  );

  ///
  wire cout0;
  wire cout1;
  wire cout2;
  /// temporary wires for carry in one-bit adder

  adder u0(a[0], b[0], cin, y[0], cout0);
  adder u1(a[1], b[1], cout0, y[1], cout1);
  adder u2(a[2], b[2], cout1, y[2], cout2);
  adder u3(a[3], b[3], cout2, y[3], cout);

endmodule

carry_select_adder/carrySelectAdder.v
`include "4bitAdder.v"
`include "mux.v"

module CSA(
    input [15:0] A,
    input [15:0] B,
    input mod, // 0:adder, 1:subtractor
    output [15:0] Y,
    output overflow
  );

  // X is used to save the modification of B for adder/subtractor.
  wire [15:0] X;

  /* These two registers are used for saving two
  	 results, induced by different carry-in, of adder. 
     4 bit of each wire is allocated for one 4-bit adder.
  */
  wire [15:0] carryzero;
  wire [15:0] carryone;

  /* 8 wires are used for saving carryout result of adders
  */
  wire c0_0, c0_1;
  wire c1_0, c1_1;
  wire c2_0, c2_1;
  wire c3_0, c3_1;

/* 3 wires for propagating each carryout of 4-bit block*/
  wire c0, c1, c2;

  wire [3:0] A0 = A[3:0];
  wire [3:0] A1 = A[7:4];
  wire [3:0] A2 = A[11:8];
  wire [3:0] A3 = A[15:12];
  // A[15:0] = {A3, A2, A1, A0}

  wire [3:0] X0 = X[3:0];
  wire [3:0] X1 = X[7:4];
  wire [3:0] X2 = X[11:8];
  wire [3:0] X3 = X[15:12];
  // X[15:0] = {X3, X2, X1, X0}

  // mod=1 chooses B for subtractor.
  mux16 s0(B, ~B, mod, X);
  
  fourBitAdder zero_0(A0, X0, 1'b0, carryzero[3:0], c0_0);
  fourBitAdder one_0(A0, X0, 1'b1, carryone[3:0], c0_1);
  mux4 m0(carryzero[3:0], carryone[3:0], c0_0, c0_1, mod, Y[3:0], c0);

  fourBitAdder zero_1(A1, X1, 1'b0, carryzero[7:4], c1_0);
  fourBitAdder one_1(A1, X1, 1'b1, carryone[7:4], c1_1);
  mux4 m1(carryzero[7:4], carryone[7:4], c1_0, c1_1, c0, Y[7:4], c1);

  fourBitAdder zero_2(A2, X2, 1'b0, carryzero[11:8], c2_0);
  fourBitAdder one_2(A2, X2, 1'b1, carryone[11:8], c2_1);
  mux4 m2(carryzero[11:8], carryone[11:8], c2_0, c2_1, c1, Y[11:8], c2);

  fourBitAdder zero_3(A3, X3, 1'b0, carryzero[15:12], c3_0);
  fourBitAdder one_3(A3, X3, 1'b1, carryone[15:12], c3_1);
  mux4 m3(carryzero[15:12], carryone[15:12], c3_0, c3_1, c2, Y[15:12], overflow);
  
endmodule

carry_select_adder/csa_tb.v
`include "carrySelectAdder.v"
`timescale 10ps / 1ps

/*
 Testbench for 16-bit carry select adder
*/


module csa_tb;

  reg [15:0] A;
  reg [15:0] B;
  reg mod;

  wire [15:0] Y;  
  wire overflow;

  initial begin

    $dumpfile("tb.vcd");
    $dumpvars(0, csa_tb);

    mod <= 0;

    A <= 16'd0;
    B <= 16'd0;


    // Check the carryout propagation
    #5;
    A <= 16'b0000_0000_0000_1100;
    B <= 16'b0000_0000_0000_1010;
    #5;
    $display("\n>> Case 1: Check the carryout propagation of [3:0]");
    $display("A: %b_%b_%b_%b  %d", A[15:12], A[11:8], A[7:4], A[3:0], A);
    $display("B: %b_%b_%b_%b  %d", B[15:12], B[11:8], B[7:4], B[3:0], B);
    $display("Y: %b_%b_%b_%b  %d", Y[15:12], Y[11:8], Y[7:4], Y[3:0], Y);

    #5;
    A <= 16'b0000_0000_1100_0100;
    B <= 16'b0000_0000_1110_0010;
    #5;
    $display("\n>> Case 2: Check the carryout propagation of [7:4]");
    $display("Propagated carryout Y[8]: %b", Y[8]);
    $display("A: %b_%b_%b_%b  %d", A[15:12], A[11:8], A[7:4], A[3:0], A);
    $display("B: %b_%b_%b_%b  %d", B[15:12], B[11:8], B[7:4], B[3:0], B);
    $display("Y: %b_%b_%b_%b  %d", Y[15:12], Y[11:8], Y[7:4], Y[3:0], Y);

    #5;
    A <= 16'b0000_1100_0100_0100;
    B <= 16'b0000_1100_0101_0010;
    #5;
    $display("\n>> Case 3: Check the carryout propagation of [11:8]");
    $display("A: %b_%b_%b_%b  %d", A[15:12], A[11:8], A[7:4], A[3:0], A);
    $display("B: %b_%b_%b_%b  %d", B[15:12], B[11:8], B[7:4], B[3:0], B);
    $display("Y: %b_%b_%b_%b  %d", Y[15:12], Y[11:8], Y[7:4], Y[3:0], Y);

    #5;
    A <= 16'b1100_0100_0100_0100;
    B <= 16'b1100_1011_0101_0010;

    #5;
    $display("\n>> Case 4: Check the overflow bit by checking the carryout propagation of [15:12]");
    $display("A:   %b_%b_%b_%b  %d", A[15:12], A[11:8], A[7:4], A[3:0], A);
    $display("B:   %b_%b_%b_%b  %d", B[15:12], B[11:8], B[7:4], B[3:0], B);
    $display("Y: %b_%b_%b_%b_%b  %d", overflow, Y[15:12], Y[11:8], Y[7:4], Y[3:0], Y);

    #5;    
    mod <= 0;
    A <= 16'b0100_1100_0100_0100;
    B <= 16'b1000_1011_0101_0110;

    #5;
    $display("\n>> Case 5: Check A + B when A > 0, B < 0");
    $display("mod: %b", mod);
    $display("A:   %b_%b_%b_%b  signed: %d", A[15:12], A[11:8], A[7:4], A[3:0], $signed(A));
    $display("B:   %b_%b_%b_%b  signed: %d", B[15:12], B[11:8], B[7:4], B[3:0], $signed(B));
    $display("Y: %b_%b_%b_%b_%b  signed: %d", overflow, Y[15:12], Y[11:8], Y[7:4], Y[3:0], $signed(Y));

    #5;    
    mod <= 0;
    A <= 16'b1000_1100_0100_0100;
    B <= 16'b0000_1011_0101_0110;

    #5;
    $display("\n>> Case 6: Check A + B when A < 0, B > 0");
    $display("mod: %b", mod);
    $display("A:   %b_%b_%b_%b  signed: %d", A[15:12], A[11:8], A[7:4], A[3:0], $signed(A));
    $display("B:   %b_%b_%b_%b  signed: %d", B[15:12], B[11:8], B[7:4], B[3:0], $signed(B));
    $display("Y: %b_%b_%b_%b_%b  signed: %d", overflow, Y[15:12], Y[11:8], Y[7:4], Y[3:0], $signed(Y));

    #5;    
    mod <= 1;
    A <= 16'b1100_1100_0100_0100;
    B <= 16'b1100_1011_0101_0110;

    #5;
    $display("\n>> Case 7: Check A - B = Y with mod = 1 when A > B");
    $display("mod: %b", mod);
    $display("A:   %b_%b_%b_%b  signed: %d", A[15:12], A[11:8], A[7:4], A[3:0], $signed(A));
    $display("B:   %b_%b_%b_%b  signed: %d", B[15:12], B[11:8], B[7:4], B[3:0], $signed(B));
    $display("Y: %b_%b_%b_%b_%b  signed: %d", overflow, Y[15:12], Y[11:8], Y[7:4], Y[3:0], $signed(Y));

    #5;    
    mod <= 1;
    A <= 16'b1111_1111_1111_1110;
    B <= 16'b1111_1111_1111_1111;

    #5;
    $display("\n>> Case 8: Check A - B= Y with mod = 1 when A < B");
    $display("mod: %b", mod);
    $display("A:   %b_%b_%b_%b  signed: %d", A[15:12], A[11:8], A[7:4], A[3:0], $signed(A));
    $display("B:   %b_%b_%b_%b  signed: %d", B[15:12], B[11:8], B[7:4], B[3:0], $signed(B));
    $display("Y: %b_%b_%b_%b_%b  signed: %d", overflow, Y[15:12], Y[11:8], Y[7:4], Y[3:0], $signed(Y));


    #5 $finish;

  end    

  CSA tb0(A, B, mod, Y, overflow);

endmodule

carry_select_adder/tb.vcd
$date
	Mon Oct 04 18:33:40 2021
$end
$version
	Icarus Verilog
$end
$timescale
	1ps
$end
$scope module csa_tb $end
$var wire 1 ! overflow $end
$var wire 16 " Y [15:0] $end
$var reg 16 # A [15:0] $end
$var reg 16 $ B [15:0] $end
$var reg 1 % mod $end
$scope module tb0 $end
$var wire 16 & A [15:0] $end
$var wire 16 ' B [15:0] $end
$var wire 1 % mod $end
$var wire 1 ! overflow $end
$var wire 16 ( carryzero [15:0] $end
$var wire 16 ) carryone [15:0] $end
$var wire 1 * c3_1 $end
$var wire 1 + c3_0 $end
$var wire 1 , c2_1 $end
$var wire 1 - c2_0 $end
$var wire 1 . c2 $end
$var wire 1 / c1_1 $end
$var wire 1 0 c1_0 $end
$var wire 1 1 c1 $end
$var wire 1 2 c0_1 $end
$var wire 1 3 c0_0 $end
$var wire 1 4 c0 $end
$var wire 16 5 Y [15:0] $end
$var wire 4 6 X3 [3:0] $end
$var wire 4 7 X2 [3:0] $end
$var wire 4 8 X1 [3:0] $end
$var wire 4 9 X0 [3:0] $end
$var wire 16 : X [15:0] $end
$var wire 4 ; A3 [3:0] $end
$var wire 4 < A2 [3:0] $end
$var wire 4 = A1 [3:0] $end
$var wire 4 > A0 [3:0] $end
$scope module m0 $end
$var wire 4 ? in0 [3:0] $end
$var wire 4 @ in1 [3:0] $end
$var wire 1 % sel $end
$var wire 4 A result [3:0] $end
$var wire 1 4 carryout $end
$var wire 1 2 carry1 $end
$var wire 1 3 carry0 $end
$upscope $end
$scope module m1 $end
$var wire 4 B in0 [3:0] $end
$var wire 4 C in1 [3:0] $end
$var wire 1 4 sel $end
$var wire 4 D result [3:0] $end
$var wire 1 1 carryout $end
$var wire 1 / carry1 $end
$var wire 1 0 carry0 $end
$upscope $end
$scope module m2 $end
$var wire 4 E in0 [3:0] $end
$var wire 4 F in1 [3:0] $end
$var wire 1 1 sel $end
$var wire 4 G result [3:0] $end
$var wire 1 . carryout $end
$var wire 1 , carry1 $end
$var wire 1 - carry0 $end
$upscope $end
$scope module m3 $end
$var wire 4 H in0 [3:0] $end
$var wire 4 I in1 [3:0] $end
$var wire 1 . sel $end
$var wire 4 J result [3:0] $end
$var wire 1 ! carryout $end
$var wire 1 * carry1 $end
$var wire 1 + carry0 $end
$upscope $end
$scope module one_0 $end
$var wire 4 K a [3:0] $end
$var wire 4 L b [3:0] $end
$var wire 1 M cin $end
$var wire 4 N y [3:0] $end
$var wire 1 O cout2 $end
$var wire 1 P cout1 $end
$var wire 1 Q cout0 $end
$var wire 1 2 cout $end
$scope module u0 $end
$var wire 1 R a $end
$var wire 1 S b $end
$var wire 1 M cin $end
$var wire 1 T y $end
$var wire 1 Q cout $end
$upscope $end
$scope module u1 $end
$var wire 1 U a $end
$var wire 1 V b $end
$var wire 1 Q cin $end
$var wire 1 W y $end
$var wire 1 P cout $end
$upscope $end
$scope module u2 $end
$var wire 1 X a $end
$var wire 1 Y b $end
$var wire 1 P cin $end
$var wire 1 Z y $end
$var wire 1 O cout $end
$upscope $end
$scope module u3 $end
$var wire 1 [ a $end
$var wire 1 \ b $end
$var wire 1 O cin $end
$var wire 1 ] y $end
$var wire 1 2 cout $end
$upscope $end
$upscope $end
$scope module one_1 $end
$var wire 4 ^ a [3:0] $end
$var wire 4 _ b [3:0] $end
$var wire 1 ` cin $end
$var wire 4 a y [3:0] $end
$var wire 1 b cout2 $end
$var wire 1 c cout1 $end
$var wire 1 d cout0 $end
$var wire 1 / cout $end
$scope module u0 $end
$var wire 1 e a $end
$var wire 1 f b $end
$var wire 1 ` cin $end
$var wire 1 g y $end
$var wire 1 d cout $end
$upscope $end
$scope module u1 $end
$var wire 1 h a $end
$var wire 1 i b $end
$var wire 1 d cin $end
$var wire 1 j y $end
$var wire 1 c cout $end
$upscope $end
$scope module u2 $end
$var wire 1 k a $end
$var wire 1 l b $end
$var wire 1 c cin $end
$var wire 1 m y $end
$var wire 1 b cout $end
$upscope $end
$scope module u3 $end
$var wire 1 n a $end
$var wire 1 o b $end
$var wire 1 b cin $end
$var wire 1 p y $end
$var wire 1 / cout $end
$upscope $end
$upscope $end
$scope module one_2 $end
$var wire 4 q a [3:0] $end
$var wire 4 r b [3:0] $end
$var wire 1 s cin $end
$var wire 4 t y [3:0] $end
$var wire 1 u cout2 $end
$var wire 1 v cout1 $end
$var wire 1 w cout0 $end
$var wire 1 , cout $end
$scope module u0 $end
$var wire 1 x a $end
$var wire 1 y b $end
$var wire 1 s cin $end
$var wire 1 z y $end
$var wire 1 w cout $end
$upscope $end
$scope module u1 $end
$var wire 1 { a $end
$var wire 1 | b $end
$var wire 1 w cin $end
$var wire 1 } y $end
$var wire 1 v cout $end
$upscope $end
$scope module u2 $end
$var wire 1 ~ a $end
$var wire 1 !" b $end
$var wire 1 v cin $end
$var wire 1 "" y $end
$var wire 1 u cout $end
$upscope $end
$scope module u3 $end
$var wire 1 #" a $end
$var wire 1 $" b $end
$var wire 1 u cin $end
$var wire 1 %" y $end
$var wire 1 , cout $end
$upscope $end
$upscope $end
$scope module one_3 $end
$var wire 4 &" a [3:0] $end
$var wire 4 '" b [3:0] $end
$var wire 1 (" cin $end
$var wire 4 )" y [3:0] $end
$var wire 1 *" cout2 $end
$var wire 1 +" cout1 $end
$var wire 1 ," cout0 $end
$var wire 1 * cout $end
$scope module u0 $end
$var wire 1 -" a $end
$var wire 1 ." b $end
$var wire 1 (" cin $end
$var wire 1 /" y $end
$var wire 1 ," cout $end
$upscope $end
$scope module u1 $end
$var wire 1 0" a $end
$var wire 1 1" b $end
$var wire 1 ," cin $end
$var wire 1 2" y $end
$var wire 1 +" cout $end
$upscope $end
$scope module u2 $end
$var wire 1 3" a $end
$var wire 1 4" b $end
$var wire 1 +" cin $end
$var wire 1 5" y $end
$var wire 1 *" cout $end
$upscope $end
$scope module u3 $end
$var wire 1 6" a $end
$var wire 1 7" b $end
$var wire 1 *" cin $end
$var wire 1 8" y $end
$var wire 1 * cout $end
$upscope $end
$upscope $end
$scope module s0 $end
$var wire 16 9" in0 [15:0] $end
$var wire 16 :" in1 [15:0] $end
$var wire 1 % mod $end
$var wire 16 ;" out [15:0] $end
$upscope $end
$scope module zero_0 $end
$var wire 4 <" a [3:0] $end
$var wire 4 =" b [3:0] $end
$var wire 1 >" cin $end
$var wire 4 ?" y [3:0] $end
$var wire 1 @" cout2 $end
$var wire 1 A" cout1 $end
$var wire 1 B" cout0 $end
$var wire 1 3 cout $end
$scope module u0 $end
$var wire 1 C" a $end
$var wire 1 D" b $end
$var wire 1 >" cin $end
$var wire 1 E" y $end
$var wire 1 B" cout $end
$upscope $end
$scope module u1 $end
$var wire 1 F" a $end
$var wire 1 G" b $end
$var wire 1 B" cin $end
$var wire 1 H" y $end
$var wire 1 A" cout $end
$upscope $end
$scope module u2 $end
$var wire 1 I" a $end
$var wire 1 J" b $end
$var wire 1 A" cin $end
$var wire 1 K" y $end
$var wire 1 @" cout $end
$upscope $end
$scope module u3 $end
$var wire 1 L" a $end
$var wire 1 M" b $end
$var wire 1 @" cin $end
$var wire 1 N" y $end
$var wire 1 3 cout $end
$upscope $end
$upscope $end
$scope module zero_1 $end
$var wire 4 O" a [3:0] $end
$var wire 4 P" b [3:0] $end
$var wire 1 Q" cin $end
$var wire 4 R" y [3:0] $end
$var wire 1 S" cout2 $end
$var wire 1 T" cout1 $end
$var wire 1 U" cout0 $end
$var wire 1 0 cout $end
$scope module u0 $end
$var wire 1 V" a $end
$var wire 1 W" b $end
$var wire 1 Q" cin $end
$var wire 1 X" y $end
$var wire 1 U" cout $end
$upscope $end
$scope module u1 $end
$var wire 1 Y" a $end
$var wire 1 Z" b $end
$var wire 1 U" cin $end
$var wire 1 [" y $end
$var wire 1 T" cout $end
$upscope $end
$scope module u2 $end
$var wire 1 \" a $end
$var wire 1 ]" b $end
$var wire 1 T" cin $end
$var wire 1 ^" y $end
$var wire 1 S" cout $end
$upscope $end
$scope module u3 $end
$var wire 1 _" a $end
$var wire 1 `" b $end
$var wire 1 S" cin $end
$var wire 1 a" y $end
$var wire 1 0 cout $end
$upscope $end
$upscope $end
$scope module zero_2 $end
$var wire 4 b" a [3:0] $end
$var wire 4 c" b [3:0] $end
$var wire 1 d" cin $end
$var wire 4 e" y [3:0] $end
$var wire 1 f" cout2 $end
$var wire 1 g" cout1 $end
$var wire 1 h" cout0 $end
$var wire 1 - cout $end
$scope module u0 $end
$var wire 1 i" a $end
$var wire 1 j" b $end
$var wire 1 d" cin $end
$var wire 1 k" y $end
$var wire 1 h" cout $end
$upscope $end
$scope module u1 $end
$var wire 1 l" a $end
$var wire 1 m" b $end
$var wire 1 h" cin $end
$var wire 1 n" y $end
$var wire 1 g" cout $end
$upscope $end
$scope module u2 $end
$var wire 1 o" a $end
$var wire 1 p" b $end
$var wire 1 g" cin $end
$var wire 1 q" y $end
$var wire 1 f" cout $end
$upscope $end
$scope module u3 $end
$var wire 1 r" a $end
$var wire 1 s" b $end
$var wire 1 f" cin $end
$var wire 1 t" y $end
$var wire 1 - cout $end
$upscope $end
$upscope $end
$scope module zero_3 $end
$var wire 4 u" a [3:0] $end
$var wire 4 v" b [3:0] $end
$var wire 1 w" cin $end
$var wire 4 x" y [3:0] $end
$var wire 1 y" cout2 $end
$var wire 1 z" cout1 $end
$var wire 1 {" cout0 $end
$var wire 1 + cout $end
$scope module u0 $end
$var wire 1 |" a $end
$var wire 1 }" b $end
$var wire 1 w" cin $end
$var wire 1 ~" y $end
$var wire 1 {" cout $end
$upscope $end
$scope module u1 $end
$var wire 1 !# a $end
$var wire 1 "# b $end
$var wire 1 {" cin $end
$var wire 1 ## y $end
$var wire 1 z" cout $end
$upscope $end
$scope module u2 $end
$var wire 1 $# a $end
$var wire 1 %# b $end
$var wire 1 z" cin $end
$var wire 1 &# y $end
$var wire 1 y" cout $end
$upscope $end
$scope module u3 $end
$var wire 1 '# a $end
$var wire 1 (# b $end
$var wire 1 y" cin $end
$var wire 1 )# y $end
$var wire 1 + cout $end
$upscope $end
$upscope $end
$upscope $end
$upscope $end
$enddefinitions $end
#0
$dumpvars
0)#
0(#
0'#
0&#
0%#
0$#
0##
0"#
0!#
0~"
0}"
0|"
0{"
0z"
0y"
b0 x"
0w"
b0 v"
b0 u"
0t"
0s"
0r"
0q"
0p"
0o"
0n"
0m"
0l"
0k"
0j"
0i"
0h"
0g"
0f"
b0 e"
0d"
b0 c"
b0 b"
0a"
0`"
0_"
0^"
0]"
0\"
0["
0Z"
0Y"
0X"
0W"
0V"
0U"
0T"
0S"
b0 R"
0Q"
b0 P"
b0 O"
0N"
0M"
0L"
0K"
0J"
0I"
0H"
0G"
0F"
0E"
0D"
0C"
0B"
0A"
0@"
b0 ?"
0>"
b0 ="
b0 <"
b0 ;"
b1111111111111111 :"
b0 9"
08"
07"
06"
05"
04"
03"
02"
01"
00"
1/"
0."
0-"
0,"
0+"
0*"
b1 )"
1("
b0 '"
b0 &"
0%"
0$"
0#"
0""
0!"
0~
0}
0|
0{
1z
0y
0x
0w
0v
0u
b1 t
1s
b0 r
b0 q
0p
0o
0n
0m
0l
0k
0j
0i
0h
1g
0f
0e
0d
0c
0b
b1 a
1`
b0 _
b0 ^
0]
0\
0[
0Z
0Y
0X
0W
0V
0U
1T
0S
0R
0Q
0P
0O
b1 N
1M
b0 L
b0 K
b0 J
b1 I
b0 H
b0 G
b1 F
b0 E
b0 D
b1 C
b0 B
b0 A
b1 @
b0 ?
b0 >
b0 =
b0 <
b0 ;
b0 :
b0 9
b0 8
b0 7
b0 6
b0 5
04
03
02
01
00
0/
0.
0-
0,
0+
0*
b1000100010001 )
b0 (
b0 '
b0 &
0%
b0 $
b0 #
b0 "
0!
$end
#50
b1 D
14
12
13
b10110 "
b10110 5
b110 A
1W
1V
1\
1H"
1G"
1M"
b111 @
b110 ?
b1010 9
b1010 L
b1010 ="
1Z
1X
b1000100010111 )
b111 N
0]
1[
1K"
1I"
b110 (
b110 ?"
0N"
1L"
b1111111111110101 :"
b1010 :
b1010 ;"
b1100 >
b1100 K
b1100 <"
b1010 $
b1010 '
b1010 9"
b1100 #
b1100 &
#150
b1 G
11
1b
1/
1S"
10
04
b110 A
b110100110 "
b110100110 5
b1010 D
1j
1i
1l
1o
1["
1Z"
1]"
1`"
0\
0M"
02
b111 @
03
b110 ?
b1011 C
b1010 B
b1110 8
b1110 _
b1110 P"
b10 9
b10 L
b10 ="
b111 N
0]
0[
b110 ?"
0N"
0L"
0m
1k
b1000110110111 )
b1011 a
1p
1n
0^"
1\"
b10100110 (
b1010 R"
1a"
1_"
b1111111100011101 :"
b11100010 :
b11100010 ;"
b100 >
b100 K
b100 <"
b1100 =
b1100 ^
b1100 O"
b11100010 $
b11100010 '
b11100010 9"
b11000100 #
b11000100 &
#250
b1 J
1d
1.
1u
1,
1f"
1-
01
b1001 D
b1100010010110 "
b1100010010110 5
b1000 G
1!"
1$"
1p"
1s"
0g
1f
1j
0i
0o
1X"
1W"
0["
0Z"
0`"
0/
b1010 C
00
b1001 B
b1001 F
b1000 E
b1100 7
b1100 r
b1100 c"
b101 8
b101 _
b101 P"
b1010 a
1p
0n
b1001 R"
1a"
0_"
0""
1~
b1100110100111 )
b1001 t
1%"
1#"
0q"
1o"
b100010010110 (
b1000 e"
1t"
1r"
b1111001110101101 :"
b110001010010 :
b110001010010 ;"
b100 =
b100 ^
b100 O"
b1100 <
b1100 q
b1100 b"
b110001010010 $
b110001010010 '
b110001010010 9"
b110001000100 #
b110001000100 &
#350
1v
1w
1!
1*"
1*
1y"
1+
1u
0f"
0.
b1111 G
b1000111110010110 "
b1000111110010110 5
b1000 J
14"
17"
1%#
1(#
0z
1y
0}
1|
0""
0!"
1k"
1j"
1n"
1m"
1q"
0p"
1,
b0 F
0-
b1111 E
b1001 I
b1000 H
b1100 6
b1100 '"
b1100 v"
b1011 7
b1011 r
b1011 c"
b0 t
0%"
0#"
b1111 e"
1t"
0r"
05"
13"
b1001000010100111 )
b1001 )"
18"
16"
0&#
1$#
b1000111110010110 (
b1000 x"
1)#
1'#
b11010010101101 :"
b1100101101010010 :
b1100101101010010 ;"
b100 <
b100 q
b100 b"
b1100 ;
b1100 &"
b1100 u"
b1100101101010010 $
b1100101101010010 '
b1100101101010010 9"
b1100010001000100 #
b1100010001000100 &
#450
b1010 A
0*"
0y"
1]
1O
b1011 @
1N"
1@"
b1010 ?
1.
b111 G
0!
b1101011110011010 "
b1101011110011010 5
b1101 J
15"
04"
1&#
0%#
b1011 N
0Z
1Y
b1010 ?"
0K"
1J"
1,
b1000 F
1-
b111 E
0*
b1101 I
0+
b1100 H
b1000 6
b1000 '"
b1000 v"
b110 9
b110 L
b110 ="
b1000 t
1%"
1#"
b111 e"
0t"
1r"
b1101100010101011 )
b1101 )"
18"
06"
b1100011110011010 (
b1100 x"
1)#
0'#
b111010010101001 :"
b1000101101010110 :
b1000101101010110 ;"
b1100 <
b1100 q
b1100 b"
b100 ;
b100 &"
b100 u"
b1000101101010110 $
b1000101101010110 '
b1000101101010110 9"
b100110001000100 #
b100110001000100 &
#550
0!
b1001011110011010 "
b1001011110011010 5
b1001 J
07"
0(#
0*
b1001 I
0+
b1000 H
b0 6
b0 '"
b0 v"
05"
03"
b1001100010101011 )
b1001 )"
18"
16"
0&#
0$#
b1000011110011010 (
b1000 x"
1)#
1'#
b1111010010101001 :"
b101101010110 :
b101101010110 ;"
b1000 ;
b1000 &"
b1000 u"
b101101010110 $
b101101010110 '
b101101010110 9"
b1000110001000100 #
b1000110001000100 &
#650
1!
0/
1+"
1,"
0w
0v
1.
b0 G
0d
0c
b1110 D
1Q
b0 J
1*
0+
1u
1,
b1 F
1f"
1-
b0 E
0b
b1111 C
0S"
b1110 B
0O
b1110 @
0@"
b1101 ?
1*"
b0 I
0y"
b1111 H
0/"
1."
02"
11"
04"
08"
07"
1~"
1}"
1##
1"#
0%#
1)#
0(#
1z
0y
0}
0|
0""
1!"
b1 t
0%"
0$"
0k"
0j"
0n"
0m"
0q"
1p"
b0 e"
0t"
0s"
1g
0f
1j
1i
1m
0l
b1111 a
1p
1o
0X"
0W"
1["
1Z"
1^"
0]"
b1110 R"
1a"
1`"
0T
1S
1W
0V
1Z
0Y
b1110 N
1]
1\
1E"
1D"
0H"
0G"
1K"
0J"
b1101 ?"
1N"
1M"
b111111110 )
b0 )"
05"
13"
b1111000011101101 (
b1111 x"
1&#
1$#
b11 6
b11 '"
b11 v"
b100 7
b100 r
b100 c"
b1010 8
b1010 _
b1010 P"
b1001 9
b1001 L
b1001 ="
b11010010101001 :"
b1100 ;
b1100 &"
b1100 u"
b11101110 "
b11101110 5
b1110 A
b11010010101001 :
b11010010101001 ;"
b1100101101010110 $
b1100101101010110 '
b1100101101010110 9"
b1100110001000100 #
b1100110001000100 &
1%
#750
0.
1,
0-
0Q
0!
0%"
1u
1t"
0f"
0O
1v
1*
0+
0."
01"
0}"
0"#
0""
0!"
1q"
0p"
0i
0o
0Z"
0`"
1T
0S
0\
0E"
0D"
0M"
1Z
0P
04
b1111 A
1d
1b
0S"
01
b1111 D
1w
b1111 G
08"
1*"
b1111111111111111 "
b1111111111111111 5
b1111 J
1)#
0y"
b0 6
b0 '"
b0 v"
b0 7
b0 r
b0 c"
b0 8
b0 _
b0 P"
b0 9
b0 L
b0 ="
02
b1111 @
03
b1110 ?
0m
1c
1/
b0 C
1^"
0T"
00
b1111 B
b0 F
b1111 E
1,"
05"
1+"
b0 I
0{"
1&#
0z"
b1111 H
b0 :
b0 ;"
1W
1U
b1111 N
1]
1[
1H"
1F"
b1110 ?"
1N"
1L"
0g
1e
0j
1h
b0 a
0p
1n
1X"
1V"
1["
1Y"
b1111 R"
1a"
1_"
0z
1x
b0 t
0}
1{
1k"
1i"
b1111 e"
1n"
1l"
0/"
1-"
b1111 )
b0 )"
02"
10"
1~"
1|"
b1111111111111110 (
b1111 x"
1##
1!#
b0 :"
b1110 >
b1110 K
b1110 <"
b1111 =
b1111 ^
b1111 O"
b1111 <
b1111 q
b1111 b"
b1111 ;
b1111 &"
b1111 u"
b1111111111111111 $
b1111111111111111 '
b1111111111111111 9"
b1111111111111110 #
b1111111111111110 &
